cnfaker/__init__.py
cnfaker/resource/.DS_Store
cnfaker/resource/IDcard.txt
cnfaker/resource/address.txt
cnfaker/resource/email.txt
cnfaker/resource/name.txt
cnfaker/resource/phone.txt
cnfaker/resource/sentence.txt
cnfaker/resource/username.txt
cnfaker-0.1.7.dist-info/DESCRIPTION.rst
cnfaker-0.1.7.dist-info/METADATA
cnfaker-0.1.7.dist-info/RECORD
cnfaker-0.1.7.dist-info/WHEEL
cnfaker-0.1.7.dist-info/metadata.json
cnfaker-0.1.7.dist-info/top_level.txt
