Metadata-Version: 2.0
Name: cnfaker
Version: 0.1.7
Summary: a library for chinese words or other things filling 
Home-page: https://github.com/hjlarry/cnfaker
Author: hjlarry
Author-email: hjlarry@163.com
License: MIT License
Keywords: faker generate chinese words
Platform: any
